json2object/__init__.py
json2object/jsontoobject.py
json2object-0.0.6.dist-info/LICENSE
json2object-0.0.6.dist-info/METADATA
json2object-0.0.6.dist-info/WHEEL
json2object-0.0.6.dist-info/top_level.txt
json2object-0.0.6.dist-info/RECORD
